pyliquibase/__init__.py
tests/__init__.py
tests/test_pyliquibase.py
pyliquibase-2.4.0.dist-info/LICENSE
pyliquibase-2.4.0.dist-info/METADATA
pyliquibase-2.4.0.dist-info/WHEEL
pyliquibase-2.4.0.dist-info/entry_points.txt
pyliquibase-2.4.0.dist-info/top_level.txt
pyliquibase-2.4.0.dist-info/RECORD
