Metadata-Version: 2.1
Name: pyliquibase
Version: 2.4.0
Summary: Python liquibase
Home-page: https://github.com/memiiso/pyliquibase
Download-URL: https://github.com/memiiso/pyliquibase/archive/master.zip
Author: Memiiso Organization
License: Apache License 2.0
Requires-Python: >=3.8
License-File: LICENSE
Requires-Dist: pyjnius ~=1.6.1
Requires-Dist: tqdm ~=4.67.1
